hectorp/__init__.py
hectorp/ammargrag.py
hectorp/ar1.py
hectorp/control.py
hectorp/convert_rlrdata2mom.py
hectorp/covariance.py
hectorp/datasnooping.py
hectorp/date2mjd.py
hectorp/designmatrix.py
hectorp/estimate_all_trends.py
hectorp/estimatespectrum.py
hectorp/estimatetrend.py
hectorp/findoffsets.py
hectorp/fullcov.py
hectorp/ggm.py
hectorp/levinson.py
hectorp/matern.py
hectorp/mjd2date.py
hectorp/mle.py
hectorp/msf.py
hectorp/msfdump.py
hectorp/msfgen.py
hectorp/my_calendar.py
hectorp/observations.py
hectorp/ols.py
hectorp/powerlaw.py
hectorp/predicttrenderror.py
hectorp/removeoutliers.py
hectorp/replace_version.py
hectorp/run_schur.py
hectorp/schur.py
hectorp/simulatenoise.py
hectorp/test_Schur.py
hectorp/varyingannual.py
hectorp/white.py
hectorp-0.1.12.dist-info/licenses/LICENSE
hectorp-0.1.12.dist-info/METADATA
hectorp-0.1.12.dist-info/WHEEL
hectorp-0.1.12.dist-info/entry_points.txt
hectorp-0.1.12.dist-info/top_level.txt
hectorp-0.1.12.dist-info/RECORD
