Metadata-Version: 2.4
Name: hectorp
Version: 0.1.12
Summary: A collection of programs to analyse geodetic time series
Home-page: https://gitlab.com/machielsimonbos/hectorp
Author: Machiel Bos
Author-email: machielbos@protonmail.com
Project-URL: Bug Tracker, https://gitlab.com/machielsimonbos/hectorp/issues
Classifier: Programming Language :: Python :: 3
Classifier: License :: OSI Approved :: GNU General Public License v3 (GPLv3)
Classifier: Operating System :: OS Independent
Requires-Python: >=3.6
License-File: LICENSE
Requires-Dist: pandas
Requires-Dist: numpy
Requires-Dist: matplotlib
Requires-Dist: scipy
Requires-Dist: mpmath
Dynamic: author
Dynamic: author-email
Dynamic: classifier
Dynamic: description
Dynamic: description-content-type
Dynamic: home-page
Dynamic: license-file
Dynamic: project-url
Dynamic: requires-dist
Dynamic: requires-python
Dynamic: summary
